setup.py
lib/__init__.py
lib/auto_script.py
lib/lambda.json
wd_accl_dev_3.egg-info/PKG-INFO
wd_accl_dev_3.egg-info/SOURCES.txt
wd_accl_dev_3.egg-info/dependency_links.txt
wd_accl_dev_3.egg-info/not-zip-safe
wd_accl_dev_3.egg-info/top_level.txt